gios/__init__.py
gios/const.py
gios/exceptions.py
gios/model.py
gios/py.typed
gios-7.0.0.dist-info/licenses/LICENSE
gios-7.0.0.dist-info/METADATA
gios-7.0.0.dist-info/WHEEL
gios-7.0.0.dist-info/top_level.txt
gios-7.0.0.dist-info/RECORD
