Metadata-Version: 2.4
Name: gios
Version: 7.0.0
Summary: Python wrapper for getting air quality data from GIOŚ servers.
Author: Maciej Bieniek
License-Expression: Apache-2.0
Project-URL: Homepage, https://github.com/bieniu/gios
Classifier: Development Status :: 5 - Production/Stable
Classifier: Operating System :: OS Independent
Classifier: Programming Language :: Python
Classifier: Programming Language :: Python :: 3
Classifier: Programming Language :: Python :: 3.13
Classifier: Programming Language :: Python :: 3.14
Classifier: Programming Language :: Python :: 3 :: Only
Classifier: Typing :: Typed
Requires-Python: >=3.13
License-File: LICENSE
Requires-Dist: aiohttp>=3.9.4
Requires-Dist: dacite>=1.7.0
Requires-Dist: yarl
Provides-Extra: test
Requires-Dist: aioresponses==0.7.8; extra == "test"
Requires-Dist: coverage==7.13.0; extra == "test"
Requires-Dist: mypy==1.19.1; extra == "test"
Requires-Dist: pytest-asyncio==1.3.0; extra == "test"
Requires-Dist: pytest-cov==7.0.0; extra == "test"
Requires-Dist: pytest-error-for-skips==2.0.2; extra == "test"
Requires-Dist: pytest-timeout==2.4.0; extra == "test"
Requires-Dist: pytest==9.0.2; extra == "test"
Requires-Dist: ruff==0.14.10; extra == "test"
Requires-Dist: syrupy==5.0.0; extra == "test"
Provides-Extra: dev
Requires-Dist: pre-commit==4.5.1; extra == "dev"
Dynamic: license-file
